wkrq/__init__.py
wkrq/__main__.py
wkrq/acrq_parser.py
wkrq/acrq_parser_simple.py
wkrq/acrq_rules.py
wkrq/acrq_semantics.py
wkrq/acrq_tableau.py
wkrq/api.py
wkrq/bilateral_equivalence.py
wkrq/cli.py
wkrq/formula.py
wkrq/llm_integration.py
wkrq/meta_sign_rules.py
wkrq/parser.py
wkrq/py.typed
wkrq/semantics.py
wkrq/signs.py
wkrq/tableau.py
wkrq/tableau_trace.py
wkrq/theory_cli.py
wkrq/theory_manager.py
wkrq/wkrq_rules.py
wkrq-3.3.1.dist-info/licenses/LICENSE
wkrq-3.3.1.dist-info/METADATA
wkrq-3.3.1.dist-info/WHEEL
wkrq-3.3.1.dist-info/entry_points.txt
wkrq-3.3.1.dist-info/top_level.txt
wkrq-3.3.1.dist-info/RECORD
