Metadata-Version: 2.4
Name: wkrq
Version: 3.3.1
Summary: A Python implementation of a semantic tableau calculus for weak Kleene logic with restricted quantification
Author-email: "Bradley P. Allen" <bradley.p.allen@gmail.com>
Maintainer-email: "Bradley P. Allen" <bradley.p.allen@gmail.com>
License-Expression: MIT
Project-URL: Homepage, https://github.com/bradleypallen/wkrq
Project-URL: Documentation, https://github.com/bradleypallen/wkrq/tree/main/docs
Project-URL: Repository, https://github.com/bradleypallen/wkrq
Project-URL: Issues, https://github.com/bradleypallen/wkrq/issues
Project-URL: Changelog, https://github.com/bradleypallen/wkrq/releases
Keywords: logic,tableau,automated-reasoning,three-valued-logic,weak-kleene,many-valued-logic,philosophical-logic,theorem-proving,paraconsistent-logic,bilateral-predicates,acrq
Classifier: Development Status :: 5 - Production/Stable
Classifier: Intended Audience :: Science/Research
Classifier: Intended Audience :: Education
Classifier: Operating System :: OS Independent
Classifier: Programming Language :: Python :: 3
Classifier: Programming Language :: Python :: 3.9
Classifier: Programming Language :: Python :: 3.10
Classifier: Programming Language :: Python :: 3.11
Classifier: Programming Language :: Python :: 3.12
Classifier: Topic :: Scientific/Engineering :: Mathematics
Classifier: Topic :: Scientific/Engineering :: Artificial Intelligence
Classifier: Topic :: Education
Classifier: Typing :: Typed
Requires-Python: >=3.9
License-File: LICENSE
Provides-Extra: dev
Requires-Dist: pytest>=7.0; extra == "dev"
Requires-Dist: pytest-cov>=4.0; extra == "dev"
Requires-Dist: black>=23.0; extra == "dev"
Requires-Dist: ruff>=0.1; extra == "dev"
Requires-Dist: mypy>=1.0; extra == "dev"
Requires-Dist: build>=0.10; extra == "dev"
Requires-Dist: twine>=4.0; extra == "dev"
Provides-Extra: llm
Requires-Dist: bilateral-truth>=0.1.0; extra == "llm"
Requires-Dist: python-dotenv>=1.0.0; extra == "llm"
Dynamic: license-file
